django_remove_field/__init__.py
django_remove_field-0.2.0.dist-info/WHEEL
django_remove_field-0.2.0.dist-info/METADATA
django_remove_field-0.2.0.dist-info/RECORD
